datahyve/__init__.py
datahyve/config.py
datahyve/constants.py
datahyve/main.py
datahyve/snowflake/__init__.py
datahyve/snowflake/connection.py
datahyve/snowflake/helpers.py
datahyve/snowflake/queries.py
datahyve/snowflake/streamer.py
datahyve/utils/__init__.py
datahyve/utils/configfiles.py
datahyve/utils/streaming.py
datahyve-0.0.2.dist-info/METADATA
datahyve-0.0.2.dist-info/WHEEL
datahyve-0.0.2.dist-info/entry_points.txt
datahyve-0.0.2.dist-info/RECORD
